File/File.py
File/__init__.py
Login_Appl/Login.py
Login_Appl/__init__.py
Login_Appl/login_holder.py
Word_Guessing/MAIN_Word_Guessing.py
Word_Guessing/Word_Guess1.py
Word_Guessing/Word_Guess2.py
Word_Guessing/__init__.py
Word_Guessing/words.py
card_creator_2/__init__.py
card_creator_2/card_creator.py
card_creator_2/utilities.py
contact_book/Contact.py
contact_book/__init__.py
semod-0.1.dist-info/LICENSE.txt
semod-0.1.dist-info/METADATA
semod-0.1.dist-info/WHEEL
semod-0.1.dist-info/top_level.txt
semod-0.1.dist-info/RECORD
